{
  "name": "Substrate Tooling",
  "slug": "substrate-tooling",
  "description": "Substrate enables developers to quickly and easily build future proof blockchains optimized for any use case.",
  "links": {
    "website": [{ "label": "substrate.io/", "url": "https://substrate.io/" }],
    "docs": [
      { "label": "Substrate Docs", "url": "https://docs.substrate.io/" }
    ],
    "explorer": [],
    "repository": [
      {
        "label": "Substrate API Sidecar",
        "url": "https://github.com/paritytech/substrate-api-sidecar"
      },
      {
        "label": "Substrate Telemetry",
        "url": "https://github.com/paritytech/substrate-telemetry"
      },
      {
        "label": "Substrate Connect",
        "url": "https://github.com/paritytech/substrate-connect"
      },
      {
        "label": "Substrate Portal UI",
        "url": "https://github.com/polkadot-js/apps"
      },
      {
        "label": "Polkadot JS Extension",
        "url": "https://github.com/polkadot-js/extension"
      }
    ],
    "social": []
  },
  "attributes": {
    "networks": [],
    "purposes": [],
    "stackLevels": ["offchain"],
    "technologies": ["substrate"],
    "types": ["library"]
  }
}
